__init__.py
gnnwr/__init__.py
gnnwr/datasets.py
gnnwr/models.py
gnnwr/networks.py
gnnwr/utils.py
gnnwr-0.1.16.dist-info/licenses/LICENSE
gnnwr-0.1.16.dist-info/METADATA
gnnwr-0.1.16.dist-info/WHEEL
gnnwr-0.1.16.dist-info/top_level.txt
gnnwr-0.1.16.dist-info/RECORD
