Metadata-Version: 2.4
Name: gnnwr
Version: 0.1.16
Summary: A pytorch implementation of the Geographically Neural Network Weighted Regression (GNNWR)
Author-email: Sensen Wu <wusensengis@zju.edu.cn>
Project-URL: Homepage, https://github.com/zjuwss/gnnwr
Project-URL: Bug Tracker, https://github.com/zjuwss/gnnwr/issues
Classifier: Programming Language :: Python :: 3
Classifier: License :: OSI Approved :: GNU General Public License v3 (GPLv3)
Classifier: Operating System :: OS Independent
Requires-Python: >=3.7
License-File: LICENSE
Requires-Dist: numpy>=1.20.0
Requires-Dist: pandas>=1.3.5
Requires-Dist: scikit_learn>=1.0.0
Requires-Dist: statsmodels>=0.13.0
Requires-Dist: torch>=1.8.1
Requires-Dist: tensorboard>=2.0.0
Requires-Dist: tqdm>=4.63.0
Requires-Dist: folium<0.19.0,>=0.12.0
Dynamic: license-file
